sc_average_overlap/__init__.py
sc_average_overlap/sc_average_overlap.py
sc_average_overlap-1.0.6.dist-info/licenses/LICENSE
sc_average_overlap-1.0.6.dist-info/METADATA
sc_average_overlap-1.0.6.dist-info/WHEEL
sc_average_overlap-1.0.6.dist-info/top_level.txt
sc_average_overlap-1.0.6.dist-info/RECORD
