Metadata-Version: 2.4
Name: sc_average_overlap
Version: 1.0.6
Summary: A tool for comparing populations in single-cell RNA-seq data with average overlap of marker gene lists
Author-email: Christopher Thai <ct647@iqb.rutgers.edu>
License: MIT License
Keywords: scRNA-seq
Classifier: License :: OSI Approved :: MIT License
Classifier: Programming Language :: Python
Classifier: Programming Language :: Python :: 3
Classifier: Topic :: Scientific/Engineering :: Bio-Informatics
Requires-Python: >=3.9
License-File: LICENSE
Requires-Dist: scanpy
Requires-Dist: anndata
Requires-Dist: numpy
Requires-Dist: pandas
Requires-Dist: scipy
Requires-Dist: seaborn
Dynamic: license-file
